cycontext/__init__.py
cycontext/context_component.py
cycontext/context_graph.py
cycontext/context_item.py
cycontext/helpers.py
cycontext/tag_object.py
cycontext/viz.py
kb/default_rules.json
kb/pneumonia_modifiers.json
cycontext-1.0.0.dist-info/LICENSE
cycontext-1.0.0.dist-info/METADATA
cycontext-1.0.0.dist-info/WHEEL
cycontext-1.0.0.dist-info/top_level.txt
cycontext-1.0.0.dist-info/RECORD
