Metadata-Version: 2.1
Name: cycontext
Version: 1.0.0
Summary: ConText algorithm using spaCy for clinical NLP
Home-page: UNKNOWN
Author: medSpaCy
Author-email: medspacy.dev@gmail.com
License: UNKNOWN
Platform: UNKNOWN
Requires-Dist: spacy (>=2.2.2)
